qiskit_research/__init__.py
qiskit_research/utils/__init__.py
qiskit_research/utils/backend.py
qiskit_research/utils/convenience.py
qiskit_research/utils/cost_funcs.py
qiskit_research/utils/dynamical_decoupling.py
qiskit_research/utils/gate_decompositions.py
qiskit_research/utils/gates.py
qiskit_research/utils/pauli_twirling.py
qiskit_research/utils/periodic_dynamical_decoupling.py
qiskit_research/utils/pulse_scaling.py
qiskit_research-0.0.4.dist-info/LICENSE.txt
qiskit_research-0.0.4.dist-info/WHEEL
qiskit_research-0.0.4.dist-info/METADATA
qiskit_research-0.0.4.dist-info/RECORD
