Metadata-Version: 2.1
Name: qiskit-research
Version: 0.0.4
Summary: Research using Qiskit, demonstrating best practices for running quantum computing experiments.
Requires-Python: >=3.8
Classifier: Intended Audience :: Developers
Classifier: Intended Audience :: Science/Research
Classifier: License :: OSI Approved :: Apache Software License
Classifier: Natural Language :: English
Classifier: Operating System :: MacOS
Classifier: Operating System :: POSIX :: Linux
Classifier: Programming Language :: Python :: 3.8
Classifier: Programming Language :: Python :: 3.9
Classifier: Programming Language :: Python :: 3.10
Classifier: Topic :: Scientific/Engineering :: Physics
Requires-Dist: qiskit==1.1.1
Requires-Dist: qiskit-aer
Requires-Dist: qiskit-ibm-runtime
Requires-Dist: black[jupyter] ; extra == "dev"
Requires-Dist: coverage ; extra == "dev"
Requires-Dist: ddt ; extra == "dev"
Requires-Dist: importlib_metadata ; extra == "dev"
Requires-Dist: mypy ; extra == "dev"
Requires-Dist: jupyter-sphinx ; extra == "dev"
Requires-Dist: nbmake ; extra == "dev"
Requires-Dist: nbsphinx ; extra == "dev"
Requires-Dist: pylint ; extra == "dev"
Requires-Dist: pytest ; extra == "dev"
Requires-Dist: qiskit[visualization] ; extra == "dev"
Requires-Dist: qiskit_sphinx_theme ; extra == "dev"
Requires-Dist: sphinx-autodoc-typehints ; extra == "dev"
Provides-Extra: dev
